MANIFEST.in
README
setup.cfg
setup.py
Rester.egg-info/PKG-INFO
Rester.egg-info/SOURCES.txt
Rester.egg-info/dependency_links.txt
Rester.egg-info/entry_points.txt
Rester.egg-info/requires.txt
Rester.egg-info/top_level.txt
rester/__init__.py
rester/apirunner.py
rester/testcase.py
rester/examples/prevoty/test_suite.json
rester/examples/prevoty/tests/xss.json