Metadata-Version: 1.0
Name: Rester
Version: 0.5.0
Summary: Rest API Testing
Home-page: https://github.com/chitamoor/rester
Author: Rajeev Chitamoor
Author-email: rajeev@chitamoor.com
License: LICENSE.txt
Platform: UNKNOWN
